{
    "cordova-plugin-whitelist": {
        "source": {
            "type": "registry",
            "id": "cordova-plugin-whitelist@1"
        },
        "is_top_level": true,
        "variables": {}
    },
    "cordova-plugin-splashscreen": {
        "source": {
            "type": "registry",
            "id": "cordova-plugin-splashscreen"
        },
        "is_top_level": true,
        "variables": {}
    },
    "org.apache.cordova.device": {
        "source": {
            "type": "registry",
            "id": "org.apache.cordova.device"
        },
        "is_top_level": true,
        "variables": {}
    },
    "com.phonegap.plugins.PushPlugin": {
        "source": {
            "type": "local",
            "path": "C:\\Users\\technolabs6\\Desktop\\com.phonegap.plugins.PushPlugin"
        },
        "is_top_level": true,
        "variables": {}
    }
}